zk/__init__.py
zk/zk.py
zk_cli-0.0.2.dist-info/METADATA
zk_cli-0.0.2.dist-info/WHEEL
zk_cli-0.0.2.dist-info/entry_points.txt
zk_cli-0.0.2.dist-info/top_level.txt
zk_cli-0.0.2.dist-info/RECORD
