Metadata-Version: 2.1
Name: zk-cli
Version: 0.0.2
Summary: A command lind utility for Zettelkasten
Home-page: https://github.com/tdfirth/zk
Author: Tom Firth
License: UNKNOWN
Platform: UNKNOWN
Classifier: Programming Language :: Python :: 3
Classifier: License :: OSI Approved :: MIT License
Classifier: Operating System :: OS Independent
Requires-Python: >=3.6
Provides-Extra: dev
Requires-Dist: nose ; extra == 'dev'
